{
  "lastRefreshed": "2026-06-28T21:45:14.610Z",
  "articles": [
    {
      "outlet": "Washington Examiner",
      "lean": "lean-right",
      "url": "https://www.washingtonexaminer.com/news/white-house/4628136/trump-meet-communist-dc-mayor-janeese-lewis-george/",
      "title": "Trump says he’ll meet with ‘communist’ DC mayoral candidate Janeese Lewis George",
      "date": "2026-06-28T21:41:47.000Z"
    },
    {
      "outlet": "The Hill",
      "lean": "center",
      "url": "https://thehill.com/homenews/administration/5944771-dc-mayor-trump-communism-threat/",
      "title": "Trump warns likely next DC mayor against 'communist' policies",
      "date": "2026-06-28T21:21:14.000Z"
    },
    {
      "outlet": "Fox News",
      "lean": "lean-right",
      "url": "https://www.foxnews.com/politics/top-democrat-lawmaker-suffers-minor-injuries-delaware-car-crash",
      "title": "Top Democrat lawmaker suffers minor injuries in Delaware car crash",
      "date": "2026-06-28T21:09:45.000Z"
    },
    {
      "outlet": "NPR",
      "lean": "lean-left",
      "url": "https://www.npr.org/2026/06/28/nx-s1-5874042/in-venezuela-silence-has-become-a-rescue-tool",
      "title": "In Venezuela, silence has become a rescue tool",
      "date": "2026-06-28T21:00:14.000Z"
    },
    {
      "outlet": "The Hill",
      "lean": "center",
      "url": "https://thehill.com/policy/healthcare/5943361-activists-maha-supreme-court-monsanto/",
      "title": "MAHA feels betrayed after Supreme Court ruling on Monsanto, glyphosate",
      "date": "2026-06-28T21:00:00.000Z"
    },
    {
      "outlet": "The Guardian (US)",
      "lean": "lean-left",
      "url": "https://www.theguardian.com/us-news/2026/jun/28/heatwave-humidity-fourth-of-july-weather",
      "title": "Heatwave and high humidity to blast much of US: ‘impactful to anyone’",
      "date": "2026-06-28T20:53:29.000Z"
    },
    {
      "outlet": "The Hill",
      "lean": "center",
      "url": "https://thehill.com/homenews/state-watch/5944737-three-firefighters-dead-colorado/",
      "title": "Three firefighters die in Colorado blaze",
      "date": "2026-06-28T20:37:58.000Z"
    },
    {
      "outlet": "The Hill",
      "lean": "center",
      "url": "https://thehill.com/homenews/senate/5944695-kaine-questions-pentagon-firings/",
      "title": "Kaine says Hegseth 'grudge' against Army looks 'personal'",
      "date": "2026-06-28T20:36:39.000Z"
    },
    {
      "outlet": "The Hill",
      "lean": "center",
      "url": "https://thehill.com/homenews/state-watch/5944404-ohio-gov-dewine-trump-tps/",
      "title": "GOP governor urges Trump to reconsider Haiti TPS after Supreme Court decision",
      "date": "2026-06-28T20:23:58.000Z"
    },
    {
      "outlet": "NPR",
      "lean": "lean-left",
      "url": "https://www.npr.org/2026/06/28/nx-s1-5828903/trump-gordie-howe-bridge-canada-blocked",
      "title": "A bridge to Canada may be blocked by the Trump administration",
      "date": "2026-06-28T20:17:22.000Z"
    },
    {
      "outlet": "Washington Examiner",
      "lean": "lean-right",
      "url": "https://www.washingtonexaminer.com/news/entertainment/4628101/naomi-lim-save-act-wont-help-republicans-win-in-november/",
      "title": "Naomi Lim: SAVE Act ‘won’t help Republicans win in November’",
      "date": "2026-06-28T20:12:07.000Z"
    },
    {
      "outlet": "Washington Examiner",
      "lean": "lean-right",
      "url": "https://www.washingtonexaminer.com/news/white-house/4628098/trump-criminally-made-algae-reflecting-pool/",
      "title": "Trump says ‘criminally made’ algae purged from Reflecting Pool",
      "date": "2026-06-28T19:59:23.000Z"
    },
    {
      "outlet": "The Hill",
      "lean": "center",
      "url": "https://thehill.com/homenews/senate/5944685-young-kelly-trump-pushback/",
      "title": "GOP senator grilled over Trump attacks on Mark Kelly",
      "date": "2026-06-28T19:57:06.000Z"
    },
    {
      "outlet": "Washington Examiner",
      "lean": "lean-right",
      "url": "https://www.washingtonexaminer.com/policy/space/4628099/nasa-rescue-mission-swift-observatory-telescope/",
      "title": "NASA launches rescue mission to stop telescope from falling back to Earth",
      "date": "2026-06-28T19:50:52.000Z"
    },
    {
      "outlet": "The Christian Science Monitor",
      "lean": "center",
      "url": "https://www.csmonitor.com/USA/Society/2026/0628/world-cup-soccer-football-questions?icid=rss",
      "title": "What's offside? And all your other World Cup questions, answered",
      "date": "2026-06-28T19:24:19.000Z"
    },
    {
      "outlet": "The Hill",
      "lean": "center",
      "url": "https://thehill.com/regulation/court-battles/5944668-tps-program-faces-termination/",
      "title": "Mullin defends Haiti TPS decision",
      "date": "2026-06-28T19:17:00.000Z"
    },
    {
      "outlet": "The Guardian (US)",
      "lean": "lean-left",
      "url": "https://www.theguardian.com/us-news/2026/jun/28/markwayne-mullin-migrants-permanent-residence-tps-ruling",
      "title": "US homeland security secretary tells migrants to seek permanent status or leave",
      "date": "2026-06-28T18:48:40.000Z"
    },
    {
      "outlet": "Washington Examiner",
      "lean": "lean-right",
      "url": "https://www.washingtonexaminer.com/news/senate/4628054/chris-murphy-socialism-mamdani-democrats/",
      "title": "Sen. Chris Murphy says socialist wins prove Democratic Party ‘alive and growing’",
      "date": "2026-06-28T18:39:25.000Z"
    },
    {
      "outlet": "The Hill",
      "lean": "center",
      "url": "https://thehill.com/homenews/administration/5944621-bipartisan-housing-bill-congress/",
      "title": "Johnson to send housing bill to Trump on Monday",
      "date": "2026-06-28T18:34:20.000Z"
    },
    {
      "outlet": "The Guardian (US)",
      "lean": "lean-left",
      "url": "https://www.theguardian.com/us-news/2026/jun/28/zohran-mamdani-new-democratic-politics",
      "title": "Zohran Mamdani says he and allies he endorsed carry a ‘national message’",
      "date": "2026-06-28T18:24:22.000Z"
    },
    {
      "outlet": "Washington Examiner",
      "lean": "lean-right",
      "url": "https://www.washingtonexaminer.com/news/entertainment/4628045/texas-democrat-defends-talarico-were-all-gay-tofu-eating-vegans/",
      "title": "Texas Democrat defends Talarico: ‘We’re all gay, tofu-eating vegans’",
      "date": "2026-06-28T18:18:22.000Z"
    },
    {
      "outlet": "PBS NewsHour",
      "lean": "center",
      "url": "https://www.pbs.org/newshour/politics/u-s-rep-julia-letlow-endorsed-by-trump-wins-the-gop-primary-for-senate-in-louisiana",
      "title": "U.S. Rep. Julia Letlow, endorsed by Trump, wins the GOP primary for Senate in Louisiana",
      "date": "2026-06-28T18:15:15.000Z"
    },
    {
      "outlet": "The Hill",
      "lean": "center",
      "url": "https://thehill.com/homenews/house/5944582-gop-rep-mark-harris-iran-war-funding/",
      "title": "House Republican says Congress 'probably' will have to use reconciliation for Iran war funding",
      "date": "2026-06-28T18:14:49.000Z"
    },
    {
      "outlet": "NPR",
      "lean": "lean-left",
      "url": "https://www.npr.org/2026/06/28/g-s1-130748/us-iran-israel-lebanon-hormuz-strikes-bahrain-kuwait",
      "title": "U.S. and Iran exchange strikes, underscoring the fragility of the ceasefire",
      "date": "2026-06-28T18:01:07.000Z"
    },
    {
      "outlet": "Washington Examiner",
      "lean": "lean-right",
      "url": "https://www.washingtonexaminer.com/premium/4619191/candidates-poor-character-problem-we-fix/",
      "title": "Governing ourselves: Candidates of poor character are a problem we the people can fix",
      "date": "2026-06-28T18:00:00.000Z"
    },
    {
      "outlet": "The Hill",
      "lean": "center",
      "url": "https://thehill.com/homenews/senate/5944561-tillis-save-act-impossible/",
      "title": "Tillis: Passing SAVE America Act before midterms is an 'impossible task'",
      "date": "2026-06-28T17:45:59.000Z"
    },
    {
      "outlet": "Washington Examiner",
      "lean": "lean-right",
      "url": "https://www.washingtonexaminer.com/news/white-house/4628044/trump-haberman-swan-regime-change-book/",
      "title": "Trump’s 2020 election loss enabled powerful second term: Haberman and Swan",
      "date": "2026-06-28T17:36:45.000Z"
    },
    {
      "outlet": "The Hill",
      "lean": "center",
      "url": "https://thehill.com/homenews/senate/5944554-chris-murphy-minimum-wage/",
      "title": "Murphy backs $25 minimum wage bill",
      "date": "2026-06-28T17:35:00.000Z"
    },
    {
      "outlet": "The Hill",
      "lean": "center",
      "url": "https://thehill.com/homenews/house/5944555-bipartisan-housing-bill-criticized/",
      "title": "Democrat says he 'wouldn't be surprised' if Trump does not sign bipartisan housing bill",
      "date": "2026-06-28T17:23:48.000Z"
    },
    {
      "outlet": "The Hill",
      "lean": "center",
      "url": "https://thehill.com/policy/healthcare/5944508-kennedy-vaccine-views-controversy/",
      "title": "GOP Sen. Cassidy seeks to explain RFK Jr. confirmation vote for Health and Human Services",
      "date": "2026-06-28T17:15:32.000Z"
    },
    {
      "outlet": "PBS NewsHour",
      "lean": "center",
      "url": "https://www.pbs.org/newshour/politics/how-the-supreme-court-decides-its-cases-a-step%e2%80%91by%e2%80%91step-guide",
      "title": "How the Supreme Court decides its cases &mdash; a step‑by‑step guide",
      "date": "2026-06-28T17:13:34.000Z"
    },
    {
      "outlet": "The Hill",
      "lean": "center",
      "url": "https://thehill.com/opinion/energy-environment/5942620-fema-flood-map-accuracy/",
      "title": "Tell Americans the truth about their flood risk",
      "date": "2026-06-28T17:00:00.000Z"
    },
    {
      "outlet": "The Hill",
      "lean": "center",
      "url": "https://thehill.com/homenews/administration/5943893-live-updates-lousiana-cassidy-trump-iran-war/",
      "title": "Live updates: Mamdani defends candidates; Cassidy criticizes Hegseth, RFK Jr.",
      "date": "2026-06-28T16:46:00.000Z"
    },
    {
      "outlet": "The Guardian (US)",
      "lean": "lean-left",
      "url": "https://www.theguardian.com/us-news/2026/jun/28/firefighter-deaths-utah-colorado-wildfires",
      "title": "Three firefighters killed and two injured while battling Utah-Colorado wildfires",
      "date": "2026-06-28T16:43:26.000Z"
    },
    {
      "outlet": "The Hill",
      "lean": "center",
      "url": "https://thehill.com/homenews/senate/5944482-cassidy-proposes-social-security-reforms/",
      "title": "Social Security's insolvency is No. 1 issue, says Sen. Bill Cassidy",
      "date": "2026-06-28T16:17:21.000Z"
    },
    {
      "outlet": "Washington Examiner",
      "lean": "lean-right",
      "url": "https://www.washingtonexaminer.com/news/campaigns/presidential/4628023/mamdani-constitution-natural-born-president/",
      "title": "Mamdani rejects idea of amending Constitution’s natural-born rule for president",
      "date": "2026-06-28T16:08:45.000Z"
    },
    {
      "outlet": "The Hill",
      "lean": "center",
      "url": "https://thehill.com/homenews/campaign/5943394-democratic-socialists-momentum-colorado-wisconsin/",
      "title": "Democratic socialists set sights beyond New York after Big Apple romp",
      "date": "2026-06-28T16:00:00.000Z"
    },
    {
      "outlet": "The Hill",
      "lean": "center",
      "url": "https://thehill.com/opinion/white-house/5943506-food-stamp-fraud-loophole/",
      "title": "The war on fraud’s coming food fight",
      "date": "2026-06-28T16:00:00.000Z"
    },
    {
      "outlet": "The Hill",
      "lean": "center",
      "url": "https://thehill.com/business/personal-finance/5934684-who-gets-an-extra-paycheck-in-july/",
      "title": "Who gets an 'extra' paycheck in July?",
      "date": "2026-06-28T16:00:00.000Z"
    },
    {
      "outlet": "Washington Examiner",
      "lean": "lean-right",
      "url": "https://www.washingtonexaminer.com/news/entertainment/4625038/what-to-know-july-4th-celebration-dc/",
      "title": "What to know about the July Fourth celebrations in DC",
      "date": "2026-06-28T16:00:00.000Z"
    },
    {
      "outlet": "The Hill",
      "lean": "center",
      "url": "https://thehill.com/policy/healthcare/5944406-vaccine-mandate-military-debate/",
      "title": "Cassidy criticizes Hegseth after flu outbreak at Texas Air Force base",
      "date": "2026-06-28T15:54:54.000Z"
    },
    {
      "outlet": "NPR",
      "lean": "lean-left",
      "url": "https://www.npr.org/2026/06/28/nx-s1-5872458/brazil-trade-us-tariffs-europe",
      "title": "Trade tensions shake up Brazil's caipirinha spirit",
      "date": "2026-06-28T15:45:42.000Z"
    },
    {
      "outlet": "The Hill",
      "lean": "center",
      "url": "https://thehill.com/homenews/senate/5944476-warnock-criticizes-vance-pope-comments/",
      "title": "Warnock on Vance criticism of Pope Leo: 'My faith is not a weapon'",
      "date": "2026-06-28T15:20:21.000Z"
    },
    {
      "outlet": "Washington Examiner",
      "lean": "lean-right",
      "url": "https://www.washingtonexaminer.com/news/campaigns/congressional/4628008/mamdani-democrats-socialist-manifesto-new-york/",
      "title": "Mamdani mocks Democrats’ anti-socialist ‘manifesto’ after New York primary wins",
      "date": "2026-06-28T15:20:12.000Z"
    },
    {
      "outlet": "Fox News",
      "lean": "lean-right",
      "url": "https://www.foxnews.com/politics/watch-biden-appears-confused-where-exit-stage-after-democratic-gala-remarks",
      "title": "WATCH: Biden appears confused about where to exit stage after Democratic gala remarks",
      "date": "2026-06-28T15:19:53.000Z"
    },
    {
      "outlet": "The Hill",
      "lean": "center",
      "url": "https://thehill.com/homenews/administration/5944466-kelly-trump-criticism-senate/",
      "title": "Kelly: Biden administration did a ‘bad job’ at the border",
      "date": "2026-06-28T15:08:09.000Z"
    },
    {
      "outlet": "The Guardian (US)",
      "lean": "lean-left",
      "url": "https://www.theguardian.com/us-news/2026/jun/28/trump-bill-cassidy-congress-iran-war",
      "title": "Bill Cassidy accuses Trump of treating Congress as ‘merely an appendage’",
      "date": "2026-06-28T15:02:27.000Z"
    },
    {
      "outlet": "Washington Examiner",
      "lean": "lean-right",
      "url": "https://www.washingtonexaminer.com/policy/immigration/4627992/ohio-mike-dewine-trump-tps-haiti/",
      "title": "Ohio’s DeWine tells Trump to ‘reconsider’ stripping TPS protections from Haitians",
      "date": "2026-06-28T15:01:51.000Z"
    },
    {
      "outlet": "The Hill",
      "lean": "center",
      "url": "https://thehill.com/opinion/healthcare/5943025-marijuana-medicine-debate-politics/",
      "title": "Rescheduling marijuana would put politics ahead of science",
      "date": "2026-06-28T15:00:00.000Z"
    },
    {
      "outlet": "The Guardian (US)",
      "lean": "lean-left",
      "url": "https://www.theguardian.com/us-news/2026/jun/28/biden-speech-trump",
      "title": "Biden calls Trump ‘a loser’, portraying him as incompetent, corrupt and vain",
      "date": "2026-06-28T14:51:42.000Z"
    },
    {
      "outlet": "The Hill",
      "lean": "center",
      "url": "https://thehill.com/homenews/senate/5944445-qatar-iran-us-negotiations/",
      "title": "GOP's Rick Scott: Qatar is not our friend",
      "date": "2026-06-28T14:46:53.000Z"
    },
    {
      "outlet": "NPR",
      "lean": "lean-left",
      "url": "https://www.npr.org/2026/06/28/g-s1-130737/wildfires-utah-colorado-firefighter-deaths-snyder",
      "title": "3 firefighters killed on Colorado-Utah border as wildfires intensify",
      "date": "2026-06-28T14:46:48.000Z"
    },
    {
      "outlet": "The Hill",
      "lean": "center",
      "url": "https://thehill.com/homenews/campaign/5944402-warnock-jeffries-dsa-debate/",
      "title": "Warnock reacts to DSA 'you're next' chants at Hakeem Jeffries",
      "date": "2026-06-28T14:37:17.000Z"
    },
    {
      "outlet": "The Hill",
      "lean": "center",
      "url": "https://thehill.com/homenews/state-watch/5944405-mayor-mamdani-trump-communism/",
      "title": "Mamdani does not support changing Constitution to allow him to run for president",
      "date": "2026-06-28T14:30:31.000Z"
    },
    {
      "outlet": "The Hill",
      "lean": "center",
      "url": "https://thehill.com/homenews/campaign/5944422-democratic-socialist-presidential-possibility/",
      "title": "Mamdani says he thinks a democratic socialist can be elected president",
      "date": "2026-06-28T14:09:07.000Z"
    },
    {
      "outlet": "The Hill",
      "lean": "center",
      "url": "https://thehill.com/opinion/healthcare/5941488-medicare-glp1-bridge-program/",
      "title": "Dr. Oz's GLP-1 Bridge could work, but it isn't a model for price controls",
      "date": "2026-06-28T14:00:00.000Z"
    },
    {
      "outlet": "The Hill",
      "lean": "center",
      "url": "https://thehill.com/opinion/technology/5942682-nasa-relativity-mars-partnership/",
      "title": "NASA extends its commercial partnerships to Mars",
      "date": "2026-06-28T14:00:00.000Z"
    },
    {
      "outlet": "The Hill",
      "lean": "center",
      "url": "https://thehill.com/homenews/administration/5944394-biden-criticizes-trump-renovations/",
      "title": "Biden rips Trump over Reflecting Pool, other DC projects: 'What a loser'",
      "date": "2026-06-28T13:57:54.000Z"
    },
    {
      "outlet": "Washington Examiner",
      "lean": "lean-right",
      "url": "https://www.washingtonexaminer.com/sports/4627981/iran-knocked-out-world-cup/",
      "title": "Iran narrowly knocked out of tumultuous World Cup on Austria’s last-second goal",
      "date": "2026-06-28T13:28:30.000Z"
    },
    {
      "outlet": "The Christian Science Monitor",
      "lean": "center",
      "url": "https://www.csmonitor.com/USA/Society/2026/0628/nasa-swift-telescope-rescue-hubble-space?icid=rss",
      "title": "NASA races to save Swift telescope from falling back to Earth with daring rescue mission",
      "date": "2026-06-28T13:18:02.000Z"
    },
    {
      "outlet": "Washington Examiner",
      "lean": "lean-right",
      "url": "https://www.washingtonexaminer.com/policy/foreign-policy/4627971/iran-us-ceasefire-hormuz-ship-strikes/",
      "title": "Iran threatens ‘complete halt’ to US peace talks after day of tit-for-tat strikes",
      "date": "2026-06-28T13:16:20.000Z"
    },
    {
      "outlet": "The Guardian (US)",
      "lean": "lean-left",
      "url": "https://www.theguardian.com/us-news/ng-interactive/2026/jun/28/america-250-origin-myth-narrative-power",
      "title": "The American myth always came at someone’s expense. Now, it’s all but collapsed",
      "date": "2026-06-28T13:00:11.000Z"
    },
    {
      "outlet": "Fox News",
      "lean": "lean-right",
      "url": "https://www.foxnews.com/politics/young-americans-break-sharply-from-older-americans-china-threat-new-poll-finds",
      "title": "Young Americans break sharply from older Americans on China threat, new poll finds",
      "date": "2026-06-28T13:00:00.000Z"
    },
    {
      "outlet": "Washington Examiner",
      "lean": "lean-right",
      "url": "https://www.washingtonexaminer.com/news/4612444/july-2026-social-security-direct-payment-three-days/",
      "title": "July Social Security direct payment worth $994 goes out in three days",
      "date": "2026-06-28T13:00:00.000Z"
    },
    {
      "outlet": "Fox News",
      "lean": "lean-right",
      "url": "https://www.foxnews.com/politics/top-usda-watchdog-warns-congress-snap-fraud-grown-far-beyond-financial-crime",
      "title": "SNAP food stamp fraud has nefarious terrorism links, top Agriculture watchdog warns Congress",
      "date": "2026-06-28T12:32:44.000Z"
    },
    {
      "outlet": "Fox News",
      "lean": "lean-right",
      "url": "https://www.foxnews.com/politics/frustrated-blue-collar-union-bosses-rip-socialist-politicians-warn-labor-exodus-dem-party",
      "title": "Frustrated blue-collar union bosses rip socialist politicians, warn of labor exodus from Dem party",
      "date": "2026-06-28T12:00:46.000Z"
    },
    {
      "outlet": "The Guardian (US)",
      "lean": "lean-left",
      "url": "https://www.theguardian.com/us-news/2026/jun/28/university-campus-civic-dialogue-industry",
      "title": "‘Dialogue is all the rage’: why is the right pouring millions into ‘civil discourse’ initiatives on US campuses?",
      "date": "2026-06-28T12:00:09.000Z"
    },
    {
      "outlet": "The Guardian (US)",
      "lean": "lean-left",
      "url": "https://www.theguardian.com/us-news/2026/jun/28/lds-church-mormon-lawsuit",
      "title": "Good-faith lawsuit? LDS church in fight with podcaster over Mormon name",
      "date": "2026-06-28T12:00:09.000Z"
    },
    {
      "outlet": "The Guardian (US)",
      "lean": "lean-left",
      "url": "https://www.theguardian.com/us-news/2026/jun/28/spirit-airlines-greyhound-bus-travel-boom",
      "title": "Spirit airlines is dead and a bus travel boom looks likely – but will Greyhounds ever be cool again?",
      "date": "2026-06-28T12:00:08.000Z"
    },
    {
      "outlet": "Washington Examiner",
      "lean": "lean-right",
      "url": "https://www.washingtonexaminer.com/restoring-america/patriotism-unity/4625645/america-250-opportunity-to-renew-civic-education-with-learning-us-history/",
      "title": "America’s 250th birthday is an opportunity to renew our commitment to civic education",
      "date": "2026-06-28T12:00:00.000Z"
    },
    {
      "outlet": "Washington Examiner",
      "lean": "lean-right",
      "url": "https://www.washingtonexaminer.com/op-eds/4626561/moving-past-5g-trump-must-lead-way-on-6g/",
      "title": "We’re already moving past 5G. Trump must lead the way on 6G",
      "date": "2026-06-28T12:00:00.000Z"
    },
    {
      "outlet": "The Guardian (US)",
      "lean": "lean-left",
      "url": "https://www.theguardian.com/football/ng-interactive/2026/jun/04/bracketology-predict-a-path-to-world-cup-victory",
      "title": "Bracketology: predict a path to World Cup victory",
      "date": "2026-06-28T11:43:13.000Z"
    },
    {
      "outlet": "The Guardian (US)",
      "lean": "lean-left",
      "url": "https://www.theguardian.com/us-news/2026/jun/28/wealth-tax-super-rich",
      "title": "When it comes to taxing the super rich, there’s no need to reinvent the wheel",
      "date": "2026-06-28T11:00:10.000Z"
    },
    {
      "outlet": "The Guardian (US)",
      "lean": "lean-left",
      "url": "https://www.theguardian.com/us-news/2026/jun/28/children-activism-social-justice",
      "title": "‘Kids are participants in the work of justice’: how US children are being folded into activism",
      "date": "2026-06-28T11:00:08.000Z"
    },
    {
      "outlet": "The Guardian (US)",
      "lean": "lean-left",
      "url": "https://www.theguardian.com/us-news/2026/jun/28/government-website-visitor-tracking-surveillance-fears",
      "title": "‘It’s dangerous and it’s going to erode trust’: redesign of US government websites stokes surveillance fears",
      "date": "2026-06-28T11:00:08.000Z"
    },
    {
      "outlet": "NPR",
      "lean": "lean-left",
      "url": "https://www.npr.org/2026/06/28/nx-s1-5847966/medical-debt-politics-republican-democrat",
      "title": "These church members disagree on politics. Together they're wiping out medical debt",
      "date": "2026-06-28T11:00:00.000Z"
    },
    {
      "outlet": "Washington Examiner",
      "lean": "lean-right",
      "url": "https://www.washingtonexaminer.com/news/world/4627542/ukraine-drone-campaign-russia-energy-infrastructure-damage/",
      "title": "Ukraine’s drone campaign against Russia’s energy infrastructure takes a toll, but falls short of a game changer",
      "date": "2026-06-28T11:00:00.000Z"
    },
    {
      "outlet": "NPR",
      "lean": "lean-left",
      "url": "https://www.npr.org/2026/06/28/nx-s1-5863039/win-the-family-cookout-with-perfectly-cooked-hot-dogs",
      "title": "Win the family cookout with perfectly cooked hot dogs",
      "date": "2026-06-28T11:00:00.000Z"
    },
    {
      "outlet": "The Guardian (US)",
      "lean": "lean-left",
      "url": "https://www.theguardian.com/world/video/2026/jun/28/us-releases-footage-it-says-shows-strikes-on-iran-video",
      "title": "US releases footage it says shows strikes on Iran – video",
      "date": "2026-06-28T10:42:27.000Z"
    },
    {
      "outlet": "The Guardian (US)",
      "lean": "lean-left",
      "url": "https://www.theguardian.com/commentisfree/2026/jun/28/reagan-jd-vance-nixon-watergate-republicans",
      "title": "Ronald Reagan to JD Vance: minimizing Watergate is a Republican tradition | Rick Perlstein",
      "date": "2026-06-28T10:00:07.000Z"
    },
    {
      "outlet": "The Guardian (US)",
      "lean": "lean-left",
      "url": "https://www.theguardian.com/us-news/2026/jun/28/ice-minnesota-defending-democracy",
      "title": "Anti-ICE organizers shift focus to defend democracy from Trump assault",
      "date": "2026-06-28T10:00:06.000Z"
    },
    {
      "outlet": "NPR",
      "lean": "lean-left",
      "url": "https://www.npr.org/2026/06/28/nx-s1-5869604/dc-fireworks-trump-250-world-record",
      "title": "July 4th fireworks in Washington: What's different for America's 250th?",
      "date": "2026-06-28T10:00:00.000Z"
    },
    {
      "outlet": "The Hill",
      "lean": "center",
      "url": "https://thehill.com/homenews/5943424-new-york-primaries-israel-divide/",
      "title": "Israel divide grows in Democratic Party after New York primaries",
      "date": "2026-06-28T10:00:00.000Z"
    },
    {
      "outlet": "The Hill",
      "lean": "center",
      "url": "https://thehill.com/homenews/administration/5943390-usps-mail-ballots-trump-order-voter-data/",
      "title": "Postmaster general's remarks on mail ballots stoke fears among voting rights advocates",
      "date": "2026-06-28T10:00:00.000Z"
    },
    {
      "outlet": "Washington Examiner",
      "lean": "lean-right",
      "url": "https://www.washingtonexaminer.com/news/4612333/first-round-july-social-security-payments-goes-out-10-days/",
      "title": "First round of July Social Security payments goes out in 10 days",
      "date": "2026-06-28T10:00:00.000Z"
    },
    {
      "outlet": "Washington Examiner",
      "lean": "lean-right",
      "url": "https://www.washingtonexaminer.com/premium/4624352/jd-vance-communion-faith-catholicism-book-review/",
      "title": "Vance finds his way home in new book, ‘Communion: Finding My Way to Faith’",
      "date": "2026-06-28T10:00:00.000Z"
    },
    {
      "outlet": "Washington Examiner",
      "lean": "lean-right",
      "url": "https://www.washingtonexaminer.com/news/campaigns/presidential/4625030/ted-cruz-2028-faith-freedom-coalition/",
      "title": "Evangelicals not sold on a Ted Cruz 2028 presidential bid",
      "date": "2026-06-28T10:00:00.000Z"
    },
    {
      "outlet": "Washington Examiner",
      "lean": "lean-right",
      "url": "https://www.washingtonexaminer.com/news/supreme-court/4626721/supreme-court-trend-biggest-cases-final-days-term/",
      "title": "Supreme Court continues trend of saving biggest cases for final days of term",
      "date": "2026-06-28T10:00:00.000Z"
    },
    {
      "outlet": "Washington Examiner",
      "lean": "lean-right",
      "url": "https://www.washingtonexaminer.com/op-eds/4626838/socialism-winning-elections-because-it-won-classrooms/",
      "title": "Socialism is winning our elections because it already won our classrooms",
      "date": "2026-06-28T10:00:00.000Z"
    },
    {
      "outlet": "Washington Examiner",
      "lean": "lean-right",
      "url": "https://www.washingtonexaminer.com/in_focus/4626849/population-controllers-abortion-movement/",
      "title": "Population controllers and the abortion movement",
      "date": "2026-06-28T10:00:00.000Z"
    },
    {
      "outlet": "Washington Examiner",
      "lean": "lean-right",
      "url": "https://www.washingtonexaminer.com/restoring-america/courage-strength-optimism/4626888/energy-investments-will-define-next-250-years/",
      "title": "American ingenuity transformed the world. Energy investments will define next 250 years",
      "date": "2026-06-28T10:00:00.000Z"
    },
    {
      "outlet": "Washington Examiner",
      "lean": "lean-right",
      "url": "https://www.washingtonexaminer.com/restoring-america/community-family/4626937/america-250-still-funding-largest-abortion-provider/",
      "title": "America at 250: Still funding its largest abortion provider",
      "date": "2026-06-28T10:00:00.000Z"
    },
    {
      "outlet": "NPR",
      "lean": "lean-left",
      "url": "https://www.npr.org/2026/06/28/g-s1-130446/fireworks-pets-dogs-cats",
      "title": "Tips for taking care of your pets when fireworks are booming",
      "date": "2026-06-28T10:00:00.000Z"
    },
    {
      "outlet": "The Guardian (US)",
      "lean": "lean-left",
      "url": "https://www.theguardian.com/football/live/2026/jun/28/world-cup-2026-england-win-clarke-quits-scotland-and-iran-denied-at-the-last-live",
      "title": "World Cup 2026: England to face DRC, South Korea president blasts team – as it happened",
      "date": "2026-06-28T09:34:50.000Z"
    },
    {
      "outlet": "The Guardian (US)",
      "lean": "lean-left",
      "url": "https://www.theguardian.com/us-news/2026/jun/28/venezuelan-earthquakes-test-trumps-new-western-hemisphere-policy-after-gutting-of-usaid",
      "title": "Venezuelan earthquakes test Trump’s new western hemisphere policy after gutting of USAID",
      "date": "2026-06-28T09:32:47.000Z"
    },
    {
      "outlet": "Washington Examiner",
      "lean": "lean-right",
      "url": "https://www.washingtonexaminer.com/premium/4611287/last-founding-father-james-monroe-paved-way-america-greatness/",
      "title": "The last Founding Father: How James Monroe paved the way for America’s greatness",
      "date": "2026-06-28T09:30:00.000Z"
    },
    {
      "outlet": "Washington Examiner",
      "lean": "lean-right",
      "url": "https://www.washingtonexaminer.com/premium/4620158/great-powers-but-for-how-long/",
      "title": "Brendan Simms’s new novel asks, have great powers returned?",
      "date": "2026-06-28T09:15:00.000Z"
    },
    {
      "outlet": "The Guardian (US)",
      "lean": "lean-left",
      "url": "https://www.theguardian.com/us-news/2026/jun/28/democratic-socialist-mayor-mamdani-wilson",
      "title": "Democratic socialists are winning in US cities with message of getting stuff done",
      "date": "2026-06-28T09:00:05.000Z"
    },
    {
      "outlet": "NPR",
      "lean": "lean-left",
      "url": "https://www.npr.org/2026/06/28/nx-s1-5843114/250-colonial-america-1776-food-anniversary",
      "title": "Food defined social hierarchy in 1776. Here's what was on the table",
      "date": "2026-06-28T09:00:00.000Z"
    },
    {
      "outlet": "NPR",
      "lean": "lean-left",
      "url": "https://www.npr.org/2026/06/28/nx-s1-5805988/cost-education-student-loan-tuition-graduate-school",
      "title": "Will the new student loan limits actually drive down tuition? Economists weigh in",
      "date": "2026-06-28T09:00:00.000Z"
    },
    {
      "outlet": "NPR",
      "lean": "lean-left",
      "url": "https://www.npr.org/2026/06/28/nx-s1-5873413/venezuela-earthquake",
      "title": "'If you are alive, make any noise': Venezuela searches rubble on day 4",
      "date": "2026-06-28T08:50:46.000Z"
    },
    {
      "outlet": "The Guardian (US)",
      "lean": "lean-left",
      "url": "https://www.theguardian.com/sport/2026/jun/28/jaron-boots-ennis-xander-zayas-quotes-post-fight-fundora-ortiz",
      "title": "‘I loved it’: Jaron Ennis says hostile crowd fueled biggest win of career",
      "date": "2026-06-28T08:45:04.000Z"
    },
    {
      "outlet": "The Guardian (US)",
      "lean": "lean-left",
      "url": "https://www.theguardian.com/football/2026/jun/28/world-cup-2026-power-rankings-france-argentina-england-scotland",
      "title": "World Cup 2026 power rankings: France still kings but who has climbed 26 places?",
      "date": "2026-06-28T08:30:04.000Z"
    },
    {
      "outlet": "Fox News",
      "lean": "lean-right",
      "url": "https://www.foxnews.com/politics/aoc-major-tech-company-on-notice-amid-looming-price-increases-far-too-big",
      "title": "AOC puts major tech company on notice amid looming price increases: 'Far too big'",
      "date": "2026-06-28T08:00:44.000Z"
    },
    {
      "outlet": "Fox News",
      "lean": "lean-right",
      "url": "https://www.foxnews.com/politics/massie-lashes-out-pressed-ex-girlfriends-allegations-affair-gop-firebrand",
      "title": "Massie lashes out when pressed on ex-girlfriend's allegations of affair with GOP firebrand",
      "date": "2026-06-28T08:00:10.000Z"
    },
    {
      "outlet": "Fox News",
      "lean": "lean-right",
      "url": "https://www.foxnews.com/politics/bill-clinton-reveals-how-he-feels-upcoming-midterms-after-socialist-victories",
      "title": "Bill Clinton reveals how he feels about upcoming midterms after socialist victories",
      "date": "2026-06-28T08:00:02.000Z"
    },
    {
      "outlet": "NPR",
      "lean": "lean-left",
      "url": "https://www.npr.org/2026/06/28/nx-s1-5872241/2026-world-cup-fifa-knockout-round-of-32",
      "title": "On to the knockout round: 4 takeaways from the FIFA World Cup so far",
      "date": "2026-06-28T07:00:00.000Z"
    },
    {
      "outlet": "The Guardian (US)",
      "lean": "lean-left",
      "url": "https://www.theguardian.com/sport/2026/jun/28/jaron-ennis-xander-zayas-fight-boxing-result",
      "title": "Jaron Ennis survives scare to stop Xander Zayas and unify 154lb titles in instant classic",
      "date": "2026-06-28T05:07:16.000Z"
    },
    {
      "outlet": "BBC News",
      "lean": "center",
      "url": "https://www.bbc.co.uk/news/articles/cdxdwkgqgq0o?at_medium=RSS&at_campaign=rss",
      "title": "US and Iran exchange strikes and accuse each other of violating ceasefire",
      "date": "2026-06-28T04:54:50.000Z"
    },
    {
      "outlet": "The Guardian (US)",
      "lean": "lean-left",
      "url": "https://www.theguardian.com/us-news/2026/jun/27/us-iran-strikes",
      "title": "US and Iran trade strikes as both sides accuse the other of endangering ceasefire",
      "date": "2026-06-28T03:09:57.000Z"
    },
    {
      "outlet": "The Hill",
      "lean": "center",
      "url": "https://thehill.com/policy/international/5944203-u-s-military-deploying-additional-resources-to-venezuela-as-earthquakes-death-toll-mounts/",
      "title": "U.S. military deploying additional resources to Venezuela as earthquakes death toll mounts",
      "date": "2026-06-28T02:03:29.000Z"
    },
    {
      "outlet": "Fox News",
      "lean": "lean-right",
      "url": "https://www.foxnews.com/politics/trump-scores-another-endorsement-win-louisiana-senate-runoff-victory",
      "title": "Trump scores another endorsement win with Louisiana Senate runoff victory",
      "date": "2026-06-28T01:49:37.000Z"
    },
    {
      "outlet": "The Hill",
      "lean": "center",
      "url": "https://thehill.com/homenews/campaign/5943183-louisiana-gop-senate-runoff/",
      "title": "Letlow wins GOP nod in Louisiana Senate race",
      "date": "2026-06-28T01:45:37.000Z"
    },
    {
      "outlet": "Fox News",
      "lean": "lean-right",
      "url": "https://www.foxnews.com/politics/louisiana-democrats-pick-rural-farmer-challenge-gop-uphill-senate-bid",
      "title": "Louisiana Democrats pick rural farmer to challenge GOP in uphill Senate bid",
      "date": "2026-06-28T01:22:38.000Z"
    },
    {
      "outlet": "Fox News",
      "lean": "lean-right",
      "url": "https://www.foxnews.com/politics/judge-rules-republican-name-sen-dan-sullivan-stay-alaska-primary-ballot",
      "title": "Judge rules Republican with same name as Sen Dan Sullivan can stay on Alaska primary ballot",
      "date": "2026-06-28T00:46:42.000Z"
    },
    {
      "outlet": "The Guardian (US)",
      "lean": "lean-left",
      "url": "https://www.theguardian.com/us-news/2026/jun/28/trump-news-at-a-glance-america-wins-either-way-vance-claims-amid-shaky-ceasefire-with-iran",
      "title": "Trump news at a glance: America wins ‘either way’, Vance claims amid shaky ceasefire with Iran",
      "date": "2026-06-28T00:18:51.000Z"
    },
    {
      "outlet": "BBC News",
      "lean": "center",
      "url": "https://www.bbc.co.uk/news/articles/cj4gqz5lx1eo?at_medium=RSS&at_campaign=rss",
      "title": "117 dead dogs found at California 'no-kill' animal rescue - many with gunshot wounds",
      "date": "2026-06-28T00:06:19.000Z"
    },
    {
      "outlet": "Fox News",
      "lean": "lean-right",
      "url": "https://www.foxnews.com/politics/mamdanis-suited-pool-plunge-overshadowed-political-clash-gop-gubernatorial-candidate",
      "title": "Mamdani's suited pool plunge overshadowed by political clash with GOP gubernatorial candidate",
      "date": "2026-06-27T23:52:56.000Z"
    },
    {
      "outlet": "The Hill",
      "lean": "center",
      "url": "https://thehill.com/homenews/state-watch/5944159-wiener-faces-protest-gaza-stance/",
      "title": "California state senator running to succeed Pelosi calls out ‘harassment’ at trans march",
      "date": "2026-06-27T23:47:09.000Z"
    },
    {
      "outlet": "The Guardian (US)",
      "lean": "lean-left",
      "url": "https://www.theguardian.com/us-news/2026/jun/27/kentucky-flood-deaths-storms",
      "title": "Four people have died from flash floods in Kentucky, governor says",
      "date": "2026-06-27T23:14:20.000Z"
    },
    {
      "outlet": "PBS NewsHour",
      "lean": "center",
      "url": "https://www.pbs.org/newshour/politics/man-with-same-name-as-u-s-sen-dan-sullivan-is-eligible-for-alaskas-primary-ballot-judge-rules",
      "title": "Man with same name as U.S. Sen. Dan Sullivan is eligible for Alaska's primary ballot, judge rules",
      "date": "2026-06-27T22:35:24.000Z"
    },
    {
      "outlet": "The Hill",
      "lean": "center",
      "url": "https://thehill.com/policy/defense/5944131-centcom-us-conducts-additional-strikes-on-iran/",
      "title": "Centcom: US conducts additional strikes on Iran",
      "date": "2026-06-27T22:18:39.000Z"
    },
    {
      "outlet": "PBS NewsHour",
      "lean": "center",
      "url": "https://www.pbs.org/newshour/politics/trump-backed-julia-letlow-faces-john-fleming-in-louisiana-gop-senate-runoff",
      "title": "Trump-backed Julia Letlow faces John Fleming in Louisiana GOP Senate runoff",
      "date": "2026-06-27T22:10:08.000Z"
    },
    {
      "outlet": "The Hill",
      "lean": "center",
      "url": "https://thehill.com/media/5944123-chuck-todd-believes-trump-pushing-murkowski-closer-to-dems/",
      "title": "Chuck Todd believes Trump pushing Murkowski closer to Dems",
      "date": "2026-06-27T22:01:59.000Z"
    },
    {
      "outlet": "NPR",
      "lean": "lean-left",
      "url": "https://www.npr.org/2026/06/27/nx-s1-5873485/trump-nominates-lance-schroyer-ice-director",
      "title": "Trump nominates former Oklahoma state trooper to head ICE",
      "date": "2026-06-27T22:01:36.000Z"
    }
  ]
}
